Metadata-Version: 1.0
Name: opendata-mos
Version: 0.3
Summary: Library for Opendata Mos
Home-page: UNKNOWN
Author: UNKNOWN
Author-email: no1ang.quadro@gmail.com
License: UNKNOWN
Platform: UNKNOWN
